czekitout/__init__.py
czekitout/check.py
czekitout/convert.py
czekitout/isa.py
czekitout/name.py
czekitout/version.py
czekitout-1.2.1.dist-info/licenses/LICENSE
czekitout-1.2.1.dist-info/METADATA
czekitout-1.2.1.dist-info/WHEEL
czekitout-1.2.1.dist-info/top_level.txt
czekitout-1.2.1.dist-info/RECORD
