Metadata-Version: 2.4
Name: czekitout
Version: 1.2.1
Summary: Contains a collection of functions that facilitate validation, and type-conversions, with useful error messages when exceptions are thrown.
Author-email: Matthew Fitzpatrick <matthew.rc.fitzpatrick@gmail.com>
Project-URL: Homepage, https://mrfitzpa.github.io/czekitout
Project-URL: Repository, https://github.com/mrfitzpa/czekitout
Keywords: type checking,type conversion
Classifier: License :: OSI Approved :: GNU General Public License v3 (GPLv3)
Classifier: Development Status :: 5 - Production/Stable
Classifier: Intended Audience :: Developers
Classifier: Programming Language :: Python
Classifier: Programming Language :: Python :: 3
Classifier: Programming Language :: Python :: 3.8
Classifier: Programming Language :: Python :: 3.9
Classifier: Programming Language :: Python :: 3.10
Classifier: Programming Language :: Python :: 3.11
Classifier: Programming Language :: Python :: 3.12
Classifier: Operating System :: OS Independent
Classifier: Natural Language :: English
Requires-Python: >=3.8
License-File: LICENSE
Requires-Dist: numpy
Provides-Extra: tests
Requires-Dist: pytest-cov; extra == "tests"
Provides-Extra: examples
Requires-Dist: jupyter; extra == "examples"
Provides-Extra: docs
Requires-Dist: sphinx; extra == "docs"
Requires-Dist: sphinx_rtd_theme; extra == "docs"
Requires-Dist: sphinx-autodoc-typehints; extra == "docs"
Requires-Dist: numpydoc; extra == "docs"
Requires-Dist: docutils; extra == "docs"
Provides-Extra: all
Requires-Dist: czekitout[docs,examples,tests]; extra == "all"
Dynamic: license-file
